psdtoolsx/__init__.py
psdtoolsx/__main__.py
psdtoolsx/api/__init__.py
psdtoolsx/api/adjustments.py
psdtoolsx/api/effects.py
psdtoolsx/api/layers.py
psdtoolsx/api/mask.py
psdtoolsx/api/numpy_io.py
psdtoolsx/api/pil_io.py
psdtoolsx/api/psd_image.py
psdtoolsx/api/shape.py
psdtoolsx/api/smart_object.py
psdtoolsx/composer/__init__.py
psdtoolsx/composer/blend.py
psdtoolsx/composer/effects.py
psdtoolsx/composer/vector.py
psdtoolsx/composite/__init__.py
psdtoolsx/composite/blend.py
psdtoolsx/composite/effects.py
psdtoolsx/composite/vector.py
psdtoolsx/compression/__init__.py
psdtoolsx/compression/_rle.pyx
psdtoolsx/compression/rle.py
psdtoolsx/constants.py
psdtoolsx/psd/__init__.py
psdtoolsx/psd/adjustments.py
psdtoolsx/psd/base.py
psdtoolsx/psd/color.py
psdtoolsx/psd/color_mode_data.py
psdtoolsx/psd/descriptor.py
psdtoolsx/psd/effects_layer.py
psdtoolsx/psd/engine_data.py
psdtoolsx/psd/filter_effects.py
psdtoolsx/psd/header.py
psdtoolsx/psd/image_data.py
psdtoolsx/psd/image_resources.py
psdtoolsx/psd/layer_and_mask.py
psdtoolsx/psd/linked_layer.py
psdtoolsx/psd/patterns.py
psdtoolsx/psd/tagged_blocks.py
psdtoolsx/psd/vector.py
psdtoolsx/terminology.py
psdtoolsx/utils.py
psdtoolsx/validators.py
psdtoolsx/version.py
psdtoolsx-19.18.0.dist-info/LICENSE.md
psdtoolsx-19.18.0.dist-info/WHEEL
psdtoolsx-19.18.0.dist-info/METADATA
psdtoolsx-19.18.0.dist-info/RECORD
