Metadata-Version: 2.1
Name: psdtoolsx
Version: 19.18.0
Summary: Python package for working with Adobe Photoshop PSD files
Home-page: https://github.com/FHPythonUtils/psdtoolsx
License: MIT
Author: FredHappyface
Requires-Python: >=3.8,<4.0
Classifier: Development Status :: 4 - Beta
Classifier: Intended Audience :: Developers
Classifier: License :: OSI Approved :: MIT License
Classifier: Programming Language :: Python
Classifier: Programming Language :: Python :: 3
Classifier: Programming Language :: Python :: 3.10
Classifier: Programming Language :: Python :: 3.8
Classifier: Programming Language :: Python :: 3.9
Classifier: Topic :: Multimedia :: Graphics
Classifier: Topic :: Multimedia :: Graphics :: Graphics Conversion
Classifier: Topic :: Multimedia :: Graphics :: Viewers
Classifier: Topic :: Software Development :: Libraries :: Python Modules
Requires-Dist: Pillow (>=9.0.0,<10)
Requires-Dist: attrs (>=21.4.0,<22)
Requires-Dist: numpy (>=1.22.1,<2)
Project-URL: Documentation, https://github.com/FHPythonUtils/psdtoolsx/blob/master/README.md
Project-URL: Repository, https://github.com/FHPythonUtils/psdtoolsx
